setup.py
easy_log/__init__.py
easy_log/config.py
easy_log/easylog.py
easy_log/utils.py
easy_log.egg-info/PKG-INFO
easy_log.egg-info/SOURCES.txt
easy_log.egg-info/dependency_links.txt
easy_log.egg-info/entry_points.txt
easy_log.egg-info/top_level.txt