Metadata-Version: 1.0
Name: easy-log
Version: 1.1.4
Summary: A log module for humans that can be used directly and easily
Home-page: https://github.com/CcccFz/easy-log
Author: CcccFz
Author-email: ccccfz@163.com
License: UNKNOWN
Platform: UNKNOWN
